<?xml version="1.0" encoding="utf-8"?>
<!DOCTYPE hibernate-mapping PUBLIC "-//Hibernate/Hibernate Mapping DTD 3.0//EN"
"http://www.hibernate.org/dtd/hibernate-mapping-3.0.dtd">
<!-- 
    Mapping file autogenerated by MyEclipse Persistence Tools
-->
<hibernate-mapping>
    <class name="com.smarthome.imcp.dao.model.bo.BoGoods" table="bo_goods">
        <id name="id" type="java.lang.Integer">
            <column name="ID" />
            <generator class="identity" />
        </id>
        <property name="goodsTitle" type="java.lang.String">
            <column name="GOODS_TITLE" length="100">
                <comment>商品标题</comment>
            </column>
        </property>
        <property name="goodsIntroduce" type="java.lang.String">
            <column name="GOODS_INTRODUCE">
                <comment>商品介绍</comment>
            </column>
        </property>
        <property name="goodsPrice" type="java.lang.Double">
            <column name="GOODS_PRICE" precision="16">
                <comment>价格</comment>
            </column>
        </property>
        <property name="goodsColor" type="java.lang.String">
            <column name="GOODS_COLOR" length="10">
                <comment>外形颜色</comment>
            </column>
        </property>
        <property name="goodsSize" type="java.lang.String">
            <column name="GOODS_SIZE" length="50">
                <comment>产品尺寸</comment>
            </column>
        </property>
        <property name="workingVoltage" type="java.lang.String">
            <column name="WORKING_VOLTAGE" length="50">
                <comment>工作电压</comment>
            </column>
        </property>
        <property name="powerConsumption" type="java.lang.String">
            <column name="POWER_CONSUMPTION" length="50">
                <comment>静态耗功</comment>
            </column>
        </property>
        <property name="materialGoods" type="java.lang.String">
            <column name="MATERIAL_GOODS" length="50">
                <comment>材质</comment>
            </column>
        </property>
        <property name="communicatuinMode" type="java.lang.String">
            <column name="COMMUNICATUIN_MODE" length="50">
                <comment>通讯方式</comment>
            </column>
        </property>
        <property name="workingTemperature" type="java.lang.String">
            <column name="WORKING_TEMPERATURE" length="50">
                <comment>工作温度</comment>
            </column>
        </property>
        <property name="workingHumidity" type="java.lang.String">
            <column name="WORKING_HUMIDITY" length="50">
                <comment>工作湿度</comment>
            </column>
        </property>
        <property name="picturesShow" type="java.lang.String">
            <column name="PICTURES_SHOW" length="500" />
        </property>
        
         <property name="salesVolumeDegree" type="java.lang.Integer">
            <column name="SALES_VOLUME_DEGREE" />
        </property>
        
        <set name="boOrders" inverse="true">
            <key>
                <column name="GOODS_ID" />
            </key>
            <one-to-many class="com.smarthome.imcp.dao.model.bo.BoOrder" />
        </set>
    </class>
</hibernate-mapping>
