<?xml version="1.0" encoding="utf-8"?>
<!DOCTYPE hibernate-mapping PUBLIC "-//Hibernate/Hibernate Mapping DTD 3.0//EN"
"http://www.hibernate.org/dtd/hibernate-mapping-3.0.dtd">
<!-- 
    Mapping file autogenerated by MyEclipse Persistence Tools
-->
<hibernate-mapping>
    <class name="com.smarthome.imcp.dao.model.bsc.BscCast" table="bsc_cast">
        <id name="castId" type="java.lang.Integer">
            <column name="CAST_ID" />
           <generator class="identity" />
        </id>
        <property name="castName" type="java.lang.String">
            <column name="CAST_NAME" length="200" />
        </property>
        <property name="totalAmount" type="java.lang.Integer">
            <column name="TOTAL_AMOUNT" />
        </property>
        <property name="castAmount" type="java.lang.Integer">
            <column name="CAST_AMOUNT" />
        </property>
        <set name="bscCastRecords" inverse="true">
            <key>
                <column name="CAST_ID" />
            </key>
            <one-to-many class="com.smarthome.imcp.dao.model.bsc.BscCastRecord" />
        </set>
    </class>
</hibernate-mapping>
